main.py
app/__init__.py
app/config.py
app/event_handler.py
app/kubernetes.py
app/commands/__init__.py
app/commands/create.py
app/commands/watch.py
kubelink-0.0.4.dist-info/LICENSE
kubelink-0.0.4.dist-info/METADATA
kubelink-0.0.4.dist-info/WHEEL
kubelink-0.0.4.dist-info/entry_points.txt
kubelink-0.0.4.dist-info/top_level.txt
kubelink-0.0.4.dist-info/RECORD
