Metadata-Version: 2.1
Name: kubelink
Version: 0.0.4
Summary: kubelink automatically sync files to kubernetes pods
Home-page: https://github.com/waverage/kubelink
Author: Volodymyr Tsumanchuk
Author-email: buorn2011@gmail.com
License: MIT
Platform: UNKNOWN
Classifier: Programming Language :: Python :: 3.7
Classifier: Operating System :: OS Independent
Requires-Python: >=3.7
License-File: LICENSE
Requires-Dist: pyyaml (==6.0)
